[
  {
    "id": "sample-math-game",
    "name": "Math Adventure",
    "description": "Practice addition and subtraction with fun animations!",
    "icon": "🔢",
    "path": "./games/sample-math-game/index.html"
  },
  {
    "id": "cat-maze-adventure",
    "name": "Cat Maze Adventure",
    "description": "Guide an orange tabby through mazes, collect fish, and avoid dogs!",
    "icon": "🐱",
    "path": "./games/cat-maze-adventure/index.html"
  },
  {
    "id": "word-wizard",
    "name": "Word Wizard",
    "description": "Learn synonyms and antonyms with progressive levels and streak bonuses!",
    "icon": "✨",
    "path": "./games/word-wizard/index.html"
  },
  {
    "id": "multiplication-master",
    "name": "Multiplication Master",
    "description": "Master times tables with achievements, streaks, and visual progress tracking!",
    "icon": "✖️",
    "path": "./games/multiplication-master/index.html"
  }
]
